hopx_mcp/__init__.py
hopx_mcp/server.py
hopx_mcp-0.2.1.dist-info/METADATA
hopx_mcp-0.2.1.dist-info/WHEEL
hopx_mcp-0.2.1.dist-info/entry_points.txt
hopx_mcp-0.2.1.dist-info/top_level.txt
hopx_mcp-0.2.1.dist-info/RECORD
