Metadata-Version: 2.4
Name: hopx-mcp
Version: 0.2.1
Summary: MCP tool for executing code in isolated environments using HopX
Requires-Python: >=3.10
Requires-Dist: hopx-ai>=0.3.0
Requires-Dist: mcp[cli]>=1.21.0
Requires-Dist: python-dotenv>=1.2.1
